genesia/clean_and_format_code.py
genesia/cli.py
genesia/run_django_server.py
genesia/templates_manager.py
genesia-0.1.14.dist-info/METADATA
genesia-0.1.14.dist-info/WHEEL
genesia-0.1.14.dist-info/entry_points.txt
genesia-0.1.14.dist-info/RECORD
